charactertrigramfuzzyset/__init__.py
charactertrigramfuzzyset-0.0.2.dist-info/METADATA
charactertrigramfuzzyset-0.0.2.dist-info/RECORD
charactertrigramfuzzyset-0.0.2.dist-info/WHEEL
charactertrigramfuzzyset-0.0.2.dist-info/top_level.txt
