Metadata-Version: 2.1
Name: charactertrigramfuzzyset
Version: 0.0.2
Summary: Character trigram fuzzy set.
Home-page: https://github.com/brymck/charactertrigramfuzzyset
Author: Bryan Lee McKelvey
Author-email: bryan.mckelvey@gmail.com
License: MIT
Platform: UNKNOWN
Classifier: License :: OSI Approved :: MIT License
Classifier: Programming Language :: Python
